tests/__init__.py
tests/test_edit_handler.py
tests/app/__init__.py
tests/app/models.py
tests/app/settings.py
tests/app/urls.py
tests/app/migrations/0001_initial.py
tests/app/migrations/__init__.py
wagtail_annotations/__init__.py
wagtail_annotations/edit_handlers.py
wagtail_annotations/fields.py
wagtail_annotations/forms.py
wagtail_annotations/views.py
wagtail_annotations/wagtail_hooks.py
wagtail_annotations/static/annotated-image/annotated-image-handler.js
wagtail_annotations/static/annotated-image/annotated-image.css
wagtail_annotations/static/annotated-image/jquery.annotate.js
wagtail_annotations/templates/annotated_image.html
wagtail_annotations/templates/annotated_image.js
wagtailannotatedimage/__init__.py
wagtailannotatedimage/edit_handlers.py
wagtailannotatedimage/fields.py
wagtailannotatedimage/forms.py
wagtailannotatedimage/views.py
wagtailannotatedimage/wagtail_hooks.py
wagtailannotatedimage/static/annotated-image/annotated-image-handler.js
wagtailannotatedimage/static/annotated-image/annotated-image.css
wagtailannotatedimage/static/annotated-image/jquery.annotate.js
wagtailannotatedimage/templates/annotated_image.html
wagtailannotatedimage/templates/annotated_image.js
wagtail_annotations-3.0.0.dist-info/LICENSE
wagtail_annotations-3.0.0.dist-info/METADATA
wagtail_annotations-3.0.0.dist-info/WHEEL
wagtail_annotations-3.0.0.dist-info/top_level.txt
wagtail_annotations-3.0.0.dist-info/RECORD
